AUTHORS
CHANGES.rst
LICENSE
MANIFEST.in
README.rst
TODO.md
debian8-dist.sh
setup.py
docs/AIMA
docs/Makefile
docs/api.rst
docs/api_TODO_MODULE_NAME.rst
docs/conf.py
docs/developer.rst
docs/index.rst
docs/init_sphinx.sh
docs/intro.rst
docs/make.bat
examples/mdp_framework_example.py
examples/optimization_framework_example.py
jdhp_pyai.egg-info/PKG-INFO
jdhp_pyai.egg-info/SOURCES.txt
jdhp_pyai.egg-info/dependency_links.txt
jdhp_pyai.egg-info/top_level.txt
pyai/__init__.py